Containerfile
HISTORY.md
LICENSE
MANIFEST.in
README.md
setup.py
protodump/VERSION
protodump/__init__.py
protodump/__main__.py
protodump/base.py
protodump/cli.py
protodump.egg-info/PKG-INFO
protodump.egg-info/SOURCES.txt
protodump.egg-info/dependency_links.txt
protodump.egg-info/entry_points.txt
protodump.egg-info/requires.txt
protodump.egg-info/top_level.txt
protodump/__pycache__/__init__.cpython-310.pyc
protodump/__pycache__/__init__.cpython-311.pyc
protodump/__pycache__/__main__.cpython-310.pyc
protodump/__pycache__/base.cpython-311.pyc
protodump/__pycache__/cli.cpython-310.pyc
protodump/__pycache__/cli.cpython-311.pyc
tests/__init__.py
tests/conftest.py
tests/test_cli.py
tests/__pycache__/__init__.cpython-311.pyc
tests/__pycache__/conftest.cpython-311-pytest-7.3.1.pyc
tests/__pycache__/test_base.cpython-311-pytest-7.3.1.pyc
tests/__pycache__/test_cli.cpython-311-pytest-7.3.1.pyc
tests/fixtures/some_test_message.proto