Metadata-Version: 2.1
Name: protodump
Version: 1.0.0
Summary: Extract protobuf definitions rom binary files.
Home-page: https://github.com/psobot/protodump/
Author: psobot
License-File: LICENSE
Requires-Dist: protobuf>3.20
Provides-Extra: test
Requires-Dist: pytest; extra == "test"
Requires-Dist: coverage; extra == "test"
Requires-Dist: ruff; extra == "test"
Requires-Dist: pytest-cov; extra == "test"
Requires-Dist: mypy; extra == "test"
Requires-Dist: gitchangelog; extra == "test"
Requires-Dist: mkdocs; extra == "test"
